[
  {
    "title": "Diabolist VR",
    "description": "Diabolist VR is a theme focused mod list that pays homage to the popular DIABLO game, it does this by adding series inspired mods and so much more!",
    "author": "ex0-tekk",
    "maintainers": [
      "github/ex0-tekk"
    ],
    "game": "skyrimvr",
    "official": true,
    "tags": [
      "Official",
      "VR",
      "Diablo Theme",
      "High Fantasy",
      "Performance",
      "PLANCK"
    ],
    "nsfw": false,
    "utility_list": false,
    "image_contains_title": true,
    "force_down": false,
    "links": {
      "image": "https://raw.githubusercontent.com/ex0-tekk/Diabolist-VR/main/DVR%20Flame%20Banner%20Header%201080.webp",
      "readme": "https://ex0-tekk.github.io/Diabolist-VR/",
      "download": "https://authored-files.wabbajack.org/Diabolist VR.wabbajack_2b819797-6f3b-498e-914d-b73a448eaad5",
      "machineURL": "diabolist_vr",
      "discordURL": "https://discord.com/invite/HuqU54gPcv"
    },
    "download_metadata": {
      "Hash": "YSLIoR8KXFM=",
      "Size": 3826604758,
      "NumberOfArchives": 892,
      "SizeOfArchives": 66790874481,
      "NumberOfInstalledFiles": 159389,
      "SizeOfInstalledFiles": 94953115944
    },
    "version": "4.0",
    "dateCreated": "1970-01-01T00:00:00Z",
    "dateUpdated": "2023-01-06T07:12:51.480147Z",
    "repositoryName": ""
  },
  {
    "title": "Legend of SkyrimVR",
    "description": "Legend of SkyrimVR is a theme focused mod list that pays homage to the popular ZELDA game, it does this by adding series inspired mods and so much more!",
    "author": "ex0-tekk",
    "maintainers": [
      "github/ex0-tekk"
    ],
    "game": "skyrimvr",
    "official": false,
    "tags": [
      "Unofficial",
      "VR",
      "Zelda Theme",
      "High Fantasy",
      "Performance",
      "PLANCK"
    ],
    "nsfw": false,
    "utility_list": false,
    "image_contains_title": true,
    "force_down": false,
    "links": {
      "image": "https://raw.githubusercontent.com/ex0-tekk/Legend-of-SkyrimVR/main/LoSVR%20Dark%20Banner%20Header%201080.webp",
      "readme": "https://ex0-tekk.github.io/Legend-of-SkyrimVR/",
      "download": "https://authored-files.wabbajack.org/Legend of SkyrimVR.wabbajack_97a89249-e638-439e-a4b0-99b685863110",
      "machineURL": "LoSVR",
      "discordURL": "https://discord.com/invite/HuqU54gPcv"
    },
    "download_metadata": {
      "Hash": "88BvLzt/VYY=",
      "Size": 5085065422,
      "NumberOfArchives": 757,
      "SizeOfArchives": 45489538365,
      "NumberOfInstalledFiles": 160093,
      "SizeOfInstalledFiles": 81808925597
    },
    "version": "3.0",
    "dateCreated": "1970-01-01T00:00:00Z",
    "dateUpdated": "2022-12-21T01:20:57.5416859Z",
    "repositoryName": ""
  }
]